[
  {
    "galaxy": "ESO563-G021",
    "corr_full": 0.9883370989484208,
    "corr_inner": 0.9893992243617502,
    "v_max": 321.0,
    "elapsed": 31.920499563217163,
    "rms_newton": 62.93505741241875,
    "rms_mond": 79.26503048414564,
    "rms_substrate": 41.89565305127958,
    "corr_newton_shape": 0.8807639209607657,
    "corr_mond_shape": 0.9481662570146053,
    "corr_substrate_shape": 0.9425931380012132,
    "winner": "SUBSTRATE",
    "outer_winner": "SUBSTRATE",
    "sub_vs_newton": 21.03940436113917,
    "sub_vs_mond": 37.36937743286606
  },
  {
    "galaxy": "IC4202",
    "corr_full": 0.9927755060309559,
    "corr_inner": 0.9946025052354237,
    "v_max": 250.0,
    "elapsed": 32.00875282287598,
    "rms_newton": 35.22311818624543,
    "rms_mond": 87.44580950984964,
    "rms_substrate": 49.61704772167004,
    "corr_newton_shape": 0.8016201559823787,
    "corr_mond_shape": 0.87169627619979,
    "corr_substrate_shape": 0.860308772639704,
    "winner": "NEWTON",
    "outer_winner": "SUBSTRATE",
    "sub_vs_newton": -14.393929535424611,
    "sub_vs_mond": 37.8287617881796
  },
  {
    "galaxy": "NGC0801",
    "corr_full": 0.9878154670674207,
    "corr_inner": 0.9923130986379821,
    "v_max": 238.0,
    "elapsed": 24.267346382141113,
    "rms_newton": 37.740963726026024,
    "rms_mond": 167.42174851836532,
    "rms_substrate": 107.18701617422076,
    "corr_newton_shape": 0.4869217094495641,
    "corr_mond_shape": 0.5805422774419533,
    "corr_substrate_shape": 0.4629894913944379,
    "winner": "NEWTON",
    "outer_winner": "NEWTON",
    "sub_vs_newton": -69.44605244819473,
    "sub_vs_mond": 60.23473234414456
  },
  {
    "galaxy": "NGC0891",
    "corr_full": 0.9882927300575227,
    "corr_inner": 0.9911690496193949,
    "v_max": 234.0,
    "elapsed": 28.873091220855713,
    "rms_newton": 69.84503892878418,
    "rms_mond": 112.71381855101775,
    "rms_substrate": 64.30006820410371,
    "corr_newton_shape": -0.02836052234354056,
    "corr_mond_shape": -0.3830354615126231,
    "corr_substrate_shape": 0.22891653249745747,
    "winner": "SUBSTRATE",
    "outer_winner": "NEWTON",
    "sub_vs_newton": 5.544970724680468,
    "sub_vs_mond": 48.41375034691404
  },
  {
    "galaxy": "NGC2683",
    "corr_full": 0.9914577287071927,
    "corr_inner": 0.9941387446990644,
    "v_max": 212.0,
    "elapsed": 22.496345043182373,
    "rms_newton": 33.117970053884335,
    "rms_mond": 139.78648238810564,
    "rms_substrate": 68.41400041944694,
    "corr_newton_shape": 0.9046930434319416,
    "corr_mond_shape": -0.7931876303296206,
    "corr_substrate_shape": 0.033137523159304266,
    "winner": "NEWTON",
    "outer_winner": "NEWTON",
    "sub_vs_newton": -35.2960303655626,
    "sub_vs_mond": 71.3724819686587
  },
  {
    "galaxy": "NGC2841",
    "corr_full": 0.9929718083751177,
    "corr_inner": 0.9916552838365029,
    "v_max": 323.0,
    "elapsed": 23.251738786697388,
    "rms_newton": 87.87483219228517,
    "rms_mond": 99.2742501756375,
    "rms_substrate": 57.104466120033095,
    "corr_newton_shape": 0.8637704897447799,
    "corr_mond_shape": -0.6918880380031609,
    "corr_substrate_shape": -0.31870075432425515,
    "winner": "SUBSTRATE",
    "outer_winner": "SUBSTRATE",
    "sub_vs_newton": 30.770366072252074,
    "sub_vs_mond": 42.16978405560441
  },
  {
    "galaxy": "NGC2955",
    "corr_full": 0.9899096302228978,
    "corr_inner": 0.9945710056915251,
    "v_max": 276.0,
    "elapsed": 22.115459442138672,
    "rms_newton": 44.136667183471666,
    "rms_mond": 107.38556347881156,
    "rms_substrate": 86.3863897729868,
    "corr_newton_shape": 0.6432254544215883,
    "corr_mond_shape": 0.7400156590675785,
    "corr_substrate_shape": 0.6303851201620518,
    "winner": "NEWTON",
    "outer_winner": "NEWTON",
    "sub_vs_newton": -42.24972258951514,
    "sub_vs_mond": 20.99917370582476
  },
  {
    "galaxy": "NGC2998",
    "corr_full": 0.9917390203898896,
    "corr_inner": 0.9966832988090631,
    "v_max": 214.0,
    "elapsed": 22.156994104385376,
    "rms_newton": 35.122227450196725,
    "rms_mond": 117.59219986808554,
    "rms_substrate": 80.11581651061772,
    "corr_newton_shape": 0.8836388177731106,
    "corr_mond_shape": 0.8899289018282867,
    "corr_substrate_shape": 0.8252796941678822,
    "winner": "NEWTON",
    "outer_winner": "SUBSTRATE",
    "sub_vs_newton": -44.993589060420994,
    "sub_vs_mond": 37.476383357467824
  },
  {
    "galaxy": "NGC3521",
    "corr_full": 0.987891593749356,
    "corr_inner": 0.989781877790136,
    "v_max": 220.0,
    "elapsed": 23.550089120864868,
    "rms_newton": 52.51577662137675,
    "rms_mond": 78.03113871399857,
    "rms_substrate": 50.63573347877452,
    "corr_newton_shape": 0.4937097188853275,
    "corr_mond_shape": 0.9617948002804323,
    "corr_substrate_shape": 0.815166292261497,
    "winner": "SUBSTRATE",
    "outer_winner": "SUBSTRATE",
    "sub_vs_newton": 1.8800431426022328,
    "sub_vs_mond": 27.395405235224054
  },
  {
    "galaxy": "NGC3953",
    "corr_full": 0.9961131241074882,
    "corr_inner": 0.9987206890425598,
    "v_max": 224.0,
    "elapsed": 22.797895431518555,
    "rms_newton": 18.26639069797791,
    "rms_mond": 85.70990747674313,
    "rms_substrate": 54.298802443664194,
    "corr_newton_shape": 0.9167134991741773,
    "corr_mond_shape": 0.8893948043630341,
    "corr_substrate_shape": 0.8237518391004627,
    "winner": "NEWTON",
    "outer_winner": "NEWTON",
    "sub_vs_newton": -36.03241174568628,
    "sub_vs_mond": 31.411105033078933
  },
  {
    "galaxy": "NGC3992",
    "corr_full": 0.9915841609456488,
    "corr_inner": 0.9932129274539984,
    "v_max": 272.0,
    "elapsed": 23.992568016052246,
    "rms_newton": 51.50181558835592,
    "rms_mond": 135.95957762574562,
    "rms_substrate": 48.53434183228801,
    "corr_newton_shape": 0.9022874068998895,
    "corr_mond_shape": -0.45942550889685435,
    "corr_substrate_shape": -0.38141518526767226,
    "winner": "SUBSTRATE",
    "outer_winner": "SUBSTRATE",
    "sub_vs_newton": 2.9674737560679105,
    "sub_vs_mond": 87.42523579345762
  },
  {
    "galaxy": "NGC4157",
    "corr_full": 0.9935366608148933,
    "corr_inner": 0.9979154675399378,
    "v_max": 201.0,
    "elapsed": 24.86137294769287,
    "rms_newton": 40.01023827592091,
    "rms_mond": 127.24162363987232,
    "rms_substrate": 43.32015318707421,
    "corr_newton_shape": 0.35098806099094115,
    "corr_mond_shape": 0.8081779708916305,
    "corr_substrate_shape": 0.6465145132376042,
    "winner": "NEWTON",
    "outer_winner": "SUBSTRATE",
    "sub_vs_newton": -3.3099149111532995,
    "sub_vs_mond": 83.9214704527981
  },
  {
    "galaxy": "NGC5005",
    "corr_full": 0.9826902668544399,
    "corr_inner": 0.9890601777411062,
    "v_max": 265.0,
    "elapsed": 22.373421907424927,
    "rms_newton": 57.02955192190641,
    "rms_mond": 84.28903357966634,
    "rms_substrate": 37.528552517978554,
    "corr_newton_shape": 0.2758503156535087,
    "corr_mond_shape": 0.9218942159401955,
    "corr_substrate_shape": 0.9175411850207125,
    "winner": "SUBSTRATE",
    "outer_winner": "SUBSTRATE",
    "sub_vs_newton": 19.500999403927857,
    "sub_vs_mond": 46.760481061687784
  },
  {
    "galaxy": "NGC5371",
    "corr_full": 0.9904323799667741,
    "corr_inner": 0.9908330151413168,
    "v_max": 242.0,
    "elapsed": 24.062947750091553,
    "rms_newton": 35.62745617971017,
    "rms_mond": 164.3239054050436,
    "rms_substrate": 73.6415516210965,
    "corr_newton_shape": 0.9246662013480915,
    "corr_mond_shape": 0.06774192343066418,
    "corr_substrate_shape": 0.016031003095744394,
    "winner": "NEWTON",
    "outer_winner": "SUBSTRATE",
    "sub_vs_newton": -38.014095441386324,
    "sub_vs_mond": 90.68235378394711
  },
  {
    "galaxy": "NGC5907",
    "corr_full": 0.9931547777823339,
    "corr_inner": 0.9977183640191007,
    "v_max": 235.0,
    "elapsed": 22.049219131469727,
    "rms_newton": 43.258327077427516,
    "rms_mond": 158.03005599490774,
    "rms_substrate": 59.57407526237687,
    "corr_newton_shape": 0.8646768271541452,
    "corr_mond_shape": -0.460697126392911,
    "corr_substrate_shape": -0.3723749304242282,
    "winner": "NEWTON",
    "outer_winner": "SUBSTRATE",
    "sub_vs_newton": -16.315748184949356,
    "sub_vs_mond": 98.45598073253086
  },
  {
    "galaxy": "NGC5985",
    "corr_full": 0.9869778845555632,
    "corr_inner": 0.9886328803893059,
    "v_max": 305.0,
    "elapsed": 23.303730487823486,
    "rms_newton": 80.13943130227766,
    "rms_mond": 54.11752576636391,
    "rms_substrate": 51.176450751299676,
    "corr_newton_shape": 0.8487875974935107,
    "corr_mond_shape": 0.701245828653273,
    "corr_substrate_shape": 0.6764364882435782,
    "winner": "SUBSTRATE",
    "outer_winner": "SUBSTRATE",
    "sub_vs_newton": 28.96298055097798,
    "sub_vs_mond": 2.9410750150642357
  },
  {
    "galaxy": "NGC6195",
    "corr_full": 0.9888203133696258,
    "corr_inner": 0.9926276519024408,
    "v_max": 258.0,
    "elapsed": 23.502979516983032,
    "rms_newton": 43.84749983065521,
    "rms_mond": 122.52829238038542,
    "rms_substrate": 72.61589206461326,
    "corr_newton_shape": 0.308261539412472,
    "corr_mond_shape": 0.6868794772957755,
    "corr_substrate_shape": 0.691784932218544,
    "winner": "NEWTON",
    "outer_winner": "SUBSTRATE",
    "sub_vs_newton": -28.768392233958053,
    "sub_vs_mond": 49.91240031577216
  },
  {
    "galaxy": "NGC6674",
    "corr_full": 0.990474070946195,
    "corr_inner": 0.9907129896502773,
    "v_max": 291.0,
    "elapsed": 23.690274715423584,
    "rms_newton": 77.68970787051921,
    "rms_mond": 181.48080332448296,
    "rms_substrate": 51.54663358819496,
    "corr_newton_shape": 0.6135575843025028,
    "corr_mond_shape": -0.2508626209447804,
    "corr_substrate_shape": 0.297375310420366,
    "winner": "SUBSTRATE",
    "outer_winner": "SUBSTRATE",
    "sub_vs_newton": 26.143074282324257,
    "sub_vs_mond": 129.934169736288
  },
  {
    "galaxy": "NGC7331",
    "corr_full": 0.9887505165843676,
    "corr_inner": 0.9908955198507403,
    "v_max": 257.0,
    "elapsed": 22.40970540046692,
    "rms_newton": 70.71859232887839,
    "rms_mond": 142.16028691006855,
    "rms_substrate": 37.25925302507296,
    "corr_newton_shape": 0.6225840456579967,
    "corr_mond_shape": 0.4506919125311302,
    "corr_substrate_shape": -0.19682686085039827,
    "winner": "SUBSTRATE",
    "outer_winner": "SUBSTRATE",
    "sub_vs_newton": 33.45933930380543,
    "sub_vs_mond": 104.9010338849956
  },
  {
    "galaxy": "NGC7814",
    "corr_full": 0.996886960454414,
    "corr_inner": 0.9941475337299606,
    "v_max": 265.0,
    "elapsed": 26.203221321105957,
    "rms_newton": 53.457344257273526,
    "rms_mond": 61.80683596781248,
    "rms_substrate": 58.47065076876517,
    "corr_newton_shape": 0.9602810663524678,
    "corr_mond_shape": 0.6911485599402213,
    "corr_substrate_shape": -0.8787051426063506,
    "winner": "NEWTON",
    "outer_winner": "SUBSTRATE",
    "sub_vs_newton": -5.013306511491642,
    "sub_vs_mond": 3.336185199047314
  },
  {
    "galaxy": "UGC02487",
    "corr_full": 0.990085501069309,
    "corr_inner": 0.9908427280329233,
    "v_max": 383.0,
    "elapsed": 32.36030912399292,
    "rms_newton": 109.51773009092928,
    "rms_mond": 135.57907410133694,
    "rms_substrate": 42.531192731055086,
    "corr_newton_shape": 0.9040773775077772,
    "corr_mond_shape": -0.8881355858697301,
    "corr_substrate_shape": -0.6415710453799739,
    "winner": "SUBSTRATE",
    "outer_winner": "SUBSTRATE",
    "sub_vs_newton": 66.98653735987419,
    "sub_vs_mond": 93.04788137028186
  },
  {
    "galaxy": "UGC02885",
    "corr_full": 0.9921712239802708,
    "corr_inner": 0.9922446719575881,
    "v_max": 305.0,
    "elapsed": 23.95415687561035,
    "rms_newton": 69.35716763455243,
    "rms_mond": 166.35253905347778,
    "rms_substrate": 62.9065257745983,
    "corr_newton_shape": -0.6682242475558027,
    "corr_mond_shape": 0.6398078658913546,
    "corr_substrate_shape": 0.19726329090188027,
    "winner": "SUBSTRATE",
    "outer_winner": "SUBSTRATE",
    "sub_vs_newton": 6.450641859954125,
    "sub_vs_mond": 103.44601327887949
  },
  {
    "galaxy": "UGC02916",
    "corr_full": 0.9869103905366233,
    "corr_inner": 0.9907856058787637,
    "v_max": 218.0,
    "elapsed": 26.751287937164307,
    "rms_newton": 39.97364888805376,
    "rms_mond": 97.11779914167609,
    "rms_substrate": 74.29192898398783,
    "corr_newton_shape": 0.488918489699297,
    "corr_mond_shape": -0.18278920915960334,
    "corr_substrate_shape": 0.13250447686332417,
    "winner": "NEWTON",
    "outer_winner": "NEWTON",
    "sub_vs_newton": -34.31828009593407,
    "sub_vs_mond": 22.825870157688257
  },
  {
    "galaxy": "UGC02953",
    "corr_full": 0.9954615073724981,
    "corr_inner": 0.9930229945284591,
    "v_max": 319.0,
    "elapsed": 22.911747694015503,
    "rms_newton": 62.22481167957494,
    "rms_mond": 103.7224328583474,
    "rms_substrate": 104.76441430712406,
    "corr_newton_shape": 0.42789032212191913,
    "corr_mond_shape": 0.4304117623107962,
    "corr_substrate_shape": 0.676680703410674,
    "winner": "NEWTON",
    "outer_winner": "SUBSTRATE",
    "sub_vs_newton": -42.539602627549115,
    "sub_vs_mond": -1.041981448776653
  },
  {
    "galaxy": "UGC03205",
    "corr_full": 0.9904948323259373,
    "corr_inner": 0.9930938378158312,
    "v_max": 237.0,
    "elapsed": 22.196800708770752,
    "rms_newton": 33.64653417615317,
    "rms_mond": 80.03726232290556,
    "rms_substrate": 74.10899030754584,
    "corr_newton_shape": 0.6289908733957917,
    "corr_mond_shape": 0.633715183890378,
    "corr_substrate_shape": 0.5910798203795152,
    "winner": "NEWTON",
    "outer_winner": "SUBSTRATE",
    "sub_vs_newton": -40.46245613139267,
    "sub_vs_mond": 5.928272015359724
  },
  {
    "galaxy": "UGC05253",
    "corr_full": 0.9881325767297504,
    "corr_inner": 0.9888864007950199,
    "v_max": 248.0,
    "elapsed": 22.0266170501709,
    "rms_newton": 44.104843857397995,
    "rms_mond": 91.10426209106662,
    "rms_substrate": 121.37005513027088,
    "corr_newton_shape": 0.7574948279930386,
    "corr_mond_shape": -0.5636590948655393,
    "corr_substrate_shape": -0.2053100877766356,
    "winner": "NEWTON",
    "outer_winner": "NEWTON",
    "sub_vs_newton": -77.26521127287289,
    "sub_vs_mond": -30.26579303920427
  },
  {
    "galaxy": "UGC08699",
    "corr_full": 0.9868341273189469,
    "corr_inner": 0.987577996158635,
    "v_max": 202.0,
    "elapsed": 22.328306674957275,
    "rms_newton": 38.29257854611432,
    "rms_mond": 67.75100771882717,
    "rms_substrate": 58.387813746296125,
    "corr_newton_shape": 0.4616546616715929,
    "corr_mond_shape": 0.20545911780921014,
    "corr_substrate_shape": -0.05016058341240798,
    "winner": "NEWTON",
    "outer_winner": "SUBSTRATE",
    "sub_vs_newton": -20.095235200181804,
    "sub_vs_mond": 9.363193972531043
  },
  {
    "galaxy": "UGC09133",
    "corr_full": 0.9969040112634573,
    "corr_inner": 0.9939589318677187,
    "v_max": 289.0,
    "elapsed": 22.276472568511963,
    "rms_newton": 61.91748044477971,
    "rms_mond": 188.608579492395,
    "rms_substrate": 122.49363021580342,
    "corr_newton_shape": 0.9338820894670661,
    "corr_mond_shape": -0.9088053487588249,
    "corr_substrate_shape": -0.5694717727546833,
    "winner": "NEWTON",
    "outer_winner": "SUBSTRATE",
    "sub_vs_newton": -60.57614977102371,
    "sub_vs_mond": 66.11494927659157
  },
  {
    "galaxy": "UGC11455",
    "corr_full": 0.9956896419429234,
    "corr_inner": 0.9996323463050619,
    "v_max": 291.0,
    "elapsed": 23.061849355697632,
    "rms_newton": 39.82149446522485,
    "rms_mond": 116.17297031694937,
    "rms_substrate": 88.53642249611194,
    "corr_newton_shape": 0.8827511112193004,
    "corr_mond_shape": 0.9659032040119779,
    "corr_substrate_shape": 0.8180692073737643,
    "winner": "NEWTON",
    "outer_winner": "NEWTON",
    "sub_vs_newton": -48.71492803088709,
    "sub_vs_mond": 27.636547820837436
  },
  {
    "galaxy": "UGC11914",
    "corr_full": 0.9904008945509709,
    "corr_inner": 0.9939008382459785,
    "v_max": 305.0,
    "elapsed": 24.48374366760254,
    "rms_newton": 20.216150253791284,
    "rms_mond": 40.26445295683908,
    "rms_substrate": 86.39497761671524,
    "corr_newton_shape": 0.8748018722259793,
    "corr_mond_shape": 0.8956279504135143,
    "corr_substrate_shape": 0.7111013997832979,
    "winner": "NEWTON",
    "outer_winner": "NEWTON",
    "sub_vs_newton": -66.17882736292395,
    "sub_vs_mond": -46.13052465987616
  },
  {
    "galaxy": "UGC12506",
    "corr_full": 0.99250870832717,
    "corr_inner": 0.9956493113445177,
    "v_max": 255.0,
    "elapsed": 21.949064254760742,
    "rms_newton": 78.84357368691505,
    "rms_mond": 126.71304299012156,
    "rms_substrate": 60.465521468264434,
    "corr_newton_shape": 0.9353874127674866,
    "corr_mond_shape": 0.7324495513237798,
    "corr_substrate_shape": 0.7743698896370473,
    "winner": "SUBSTRATE",
    "outer_winner": "SUBSTRATE",
    "sub_vs_newton": 18.378052218650616,
    "sub_vs_mond": 66.24752152185712
  }
]